etag_cache/__init__.py
etag_cache/etag_package.py
etag_cache-0.2.dist-info/LICENSE
etag_cache-0.2.dist-info/METADATA
etag_cache-0.2.dist-info/WHEEL
etag_cache-0.2.dist-info/top_level.txt
etag_cache-0.2.dist-info/RECORD
