Metadata-Version: 2.1
Name: etag-cache
Version: 0.2
Summary: Python package for caching HTTP response based on etag
Home-page: https://github.com/ranjanrak/etag-response-cache
Author: Rakesh R
Author-email: rrrakesh265@gmail.com
License: MIT
Platform: UNKNOWN
Classifier: Programming Language :: Python :: 3.6
Classifier: License :: OSI Approved :: MIT License
Classifier: Topic :: Software Development :: Libraries
